[
  {
    "title": "KnowNative",
    "description": "",
    "tech": [],
    "website": "",
    "github": "",
    "challenges": "",
    "lessons": ""
  },
  {
    "title": "WanderWise",
    "description": "",
    "tech": [],
    "website": "",
    "github": "",
    "challenges": "",
    "lessons": ""
  },
  {
    "title": "Order-Eatz",
    "description": "",
    "tech": [],
    "website": "",
    "github": "",
    "challenges": "",
    "lessons": ""
  },
  {
    "title": "SweatShare",
    "description": "",
    "tech": [],
    "website": "",
    "github": "",
    "challenges": "",
    "lessons": ""
  },
  {
    "title": "Pokemon Trivia Game",
    "description": "",
    "tech": [],
    "website": "",
    "github": "",
    "challenges": "",
    "lessons": ""
  }
]
